paseos/__init__.py
paseos/paseos.py
paseos/activities/activity_manager.py
paseos/activities/activity_processor.py
paseos/activities/activity_runner.py
paseos/actors/actor_builder.py
paseos/actors/base_actor.py
paseos/actors/ground_station_actor.py
paseos/actors/spacecraft_actor.py
paseos/central_body/central_body.py
paseos/central_body/is_in_line_of_sight.py
paseos/central_body/mesh_between_points.py
paseos/central_body/sphere_between_points.py
paseos/communication/find_next_window.py
paseos/communication/get_communication_window.py
paseos/power/charge_model.py
paseos/power/discharge_model.py
paseos/power/power_device_type.py
paseos/radiation/radiation_model.py
paseos/resources/de421.bsp
paseos/resources/default_cfg.toml
paseos/thermal/thermal_model.py
paseos/utils/check_cfg.py
paseos/utils/load_default_cfg.py
paseos/utils/operations_monitor.py
paseos/utils/reference_frame.py
paseos/utils/set_log_level.py
paseos/visualization/animation.py
paseos/visualization/plot.py
paseos/visualization/space_animation.py
paseos-0.2.0.dist-info/LICENSE
paseos-0.2.0.dist-info/METADATA
paseos-0.2.0.dist-info/WHEEL
paseos-0.2.0.dist-info/top_level.txt
paseos-0.2.0.dist-info/RECORD
