Metadata-Version: 2.1
Name: paseos
Version: 0.2.0
Summary: A package which simulates the space environment for operating multiple spacecraft.
Home-page: https://github.com/aidotse/paseos
Author: Φ-lab@Sweden
Author-email: pablo.gomez@esa.int
License: UNKNOWN
Project-URL: Source, https://github.com/aidotse/paseos/
Platform: UNKNOWN
Classifier: Development Status :: 3 - Alpha
Classifier: Intended Audience :: Developers
Classifier: Intended Audience :: Science/Research
Classifier: Topic :: Scientific/Engineering :: Mathematics
Classifier: License :: OSI Approved :: GNU General Public License v3 (GPLv3)
Classifier: Programming Language :: Python :: 3.8
Classifier: Programming Language :: Python :: 3.9
Requires-Python: >=3.8
Requires-Dist: dotmap >=1.3.30
Requires-Dist: loguru >=0.6.0
Requires-Dist: matplotlib >=3.6.0
Requires-Dist: numpy ==1.23.5
Requires-Dist: pykep >=2.6
Requires-Dist: pyquaternion >=0.9.9
Requires-Dist: scikit-spatial >=6.5.0
Requires-Dist: skyfield >=1.45
Requires-Dist: toml >=0.10.2
Requires-Dist: tqdm >=4.64.1
